trexprinterapi/API.py
trexprinterapi/__init__.py
trexprinterapi/patterns.py
trexprinterapi/utils.py
trexprinterapi-0.0.2.dist-info/METADATA
trexprinterapi-0.0.2.dist-info/WHEEL
trexprinterapi-0.0.2.dist-info/licenses/LICENSE
trexprinterapi-0.0.2.dist-info/RECORD
