Metadata-Version: 2.1
Name: trexprinterapi
Version: 0.0.2
Summary: Project to make API for Bresser 3D printer
Project-URL: Homepage, https://github.com/Chris112358/TRex_Printer_API
Project-URL: Bug Tracker, https://github.com/Chris112358/TRex_Printer_API/issues
Author: Christian
License-File: LICENSE
Classifier: License :: OSI Approved :: GNU General Public License v3 or later (GPLv3+)
Classifier: Operating System :: OS Independent
Classifier: Programming Language :: Python :: 3
Requires-Python: >=3.7
